odoo/addons/hr_attendance_hour_type_report/README.rst
odoo/addons/hr_attendance_hour_type_report/__init__.py
odoo/addons/hr_attendance_hour_type_report/__manifest__.py
odoo/addons/hr_attendance_hour_type_report/i18n/es.po
odoo/addons/hr_attendance_hour_type_report/i18n/fr.po
odoo/addons/hr_attendance_hour_type_report/i18n/hr_attendance_hour_type_report.pot
odoo/addons/hr_attendance_hour_type_report/i18n/it.po
odoo/addons/hr_attendance_hour_type_report/models/__init__.py
odoo/addons/hr_attendance_hour_type_report/models/hr_attendance.py
odoo/addons/hr_attendance_hour_type_report/models/res_company.py
odoo/addons/hr_attendance_hour_type_report/models/res_config.py
odoo/addons/hr_attendance_hour_type_report/readme/CONFIGURE.rst
odoo/addons/hr_attendance_hour_type_report/readme/CONTRIBUTORS.rst
odoo/addons/hr_attendance_hour_type_report/readme/DESCRIPTION.rst
odoo/addons/hr_attendance_hour_type_report/readme/USAGE.rst
odoo/addons/hr_attendance_hour_type_report/static/description/icon.png
odoo/addons/hr_attendance_hour_type_report/static/description/index.html
odoo/addons/hr_attendance_hour_type_report/tests/__init__.py
odoo/addons/hr_attendance_hour_type_report/tests/test_attendance.py
odoo/addons/hr_attendance_hour_type_report/views/hr_attendance.xml
odoo/addons/hr_attendance_hour_type_report/views/res_config_settings.xml
odoo14_addon_hr_attendance_hour_type_report-14.0.1.0.1.dev16.dist-info/METADATA
odoo14_addon_hr_attendance_hour_type_report-14.0.1.0.1.dev16.dist-info/WHEEL
odoo14_addon_hr_attendance_hour_type_report-14.0.1.0.1.dev16.dist-info/top_level.txt
odoo14_addon_hr_attendance_hour_type_report-14.0.1.0.1.dev16.dist-info/RECORD
